{
  "name": "mesquite-logmesquite_logvash",
  "inference": {
    "method": "stan_sampling",
    "method_arguments": {
      "chains": 10,
      "iter": 20000,
      "warmup": 10000,
      "thin": 10,
      "seed": 4711,
      "control": {
        "adapt_delta": 0.8
      },
      "verbose": true
    }
  },
  "diagnostics": {
    "diagnostic_information": {
      "names": ["beta[1]", "beta[2]", "beta[3]", "beta[4]", "beta[5]", "beta[6]", "sigma"]
    },
    "ndraws": 10000,
    "nchains": 10,
    "effective_sample_size_bulk": [9941.95859149324, 10239.2113387544, 9962.04073811025, 9897.82197982954, 10301.3842436712, 10085.9916057027, 9961.04692441681],
    "effective_sample_size_tail": [9888.8354640307, 9573.20598895378, 9697.89484121671, 9871.69353977128, 10005.9680932562, 9998.5645702976, 9746.22338109091],
    "r_hat": [0.999936731082165, 0.999782726662317, 0.999804532507452, 1.00085986221854, 1.0005288662493, 0.999953354906564, 0.999468941660096],
    "divergent_transitions": [0, 0, 0, 0, 0, 0, 0, 0, 0, 0],
    "expected_fraction_of_missing_information": [2.03378202352847, 1.99332363111191, 2.07107695751308, 1.90518307919104, 1.95489056802301, 1.93876672621769, 2.05563229707884, 1.92762699144291, 1.99655106970306, 2.03641775744154]
  },
  "checks_made": {
    "ndraws_is_gte_10k": true,
    "nchains_is_gte_4": true,
    "ess_within_bounds": true,
    "r_hat_below_1_01": true,
    "efmi_above_0_2": true
  },
  "comments": null,
  "added_by": "Oliver Järnefelt",
  "added_date": "2020-05-06",
  "versions": {
    "rstan_version": "rstan 2.19.2",
    "r_Makevars": "\nCXX14FLAGS=-O3 -march=native -mtune=native -fPIC\nCXX14=g++",
    "r_version": "R version 3.6.1 (2019-07-05)",
    "r_session": "R version 3.6.1 (2019-07-05)\nPlatform: x86_64-pc-linux-gnu (64-bit)\nRunning under: Ubuntu 16.04.6 LTS\n\nMatrix products: default\nBLAS:   /usr/lib/libblas/libblas.so.3.6.0\nLAPACK: /usr/lib/lapack/liblapack.so.3.6.0\n\nlocale:\n [1] LC_CTYPE=en_US.UTF-8       LC_NUMERIC=C               LC_TIME=fi_FI.UTF-8        LC_COLLATE=en_US.UTF-8    \n [5] LC_MONETARY=fi_FI.UTF-8    LC_MESSAGES=en_US.UTF-8    LC_PAPER=fi_FI.UTF-8       LC_NAME=C                 \n [9] LC_ADDRESS=C               LC_TELEPHONE=C             LC_MEASUREMENT=fi_FI.UTF-8 LC_IDENTIFICATION=C       \n\nattached base packages:\n[1] stats     graphics  grDevices utils     datasets  methods   base     \n\nother attached packages:\n[1] posterior_0.0.1    posteriordb_0.1    rstan_2.19.2       ggplot2_3.2.1      StanHeaders_2.19.0\n\nloaded via a namespace (and not attached):\n [1] Rcpp_1.0.2         pillar_1.4.2       compiler_3.6.1     prettyunits_1.0.2  tools_3.6.1        pkgbuild_1.0.6    \n [7] checkmate_2.0.0    tibble_2.1.3       gtable_0.3.0       pkgconfig_2.0.3    rlang_0.4.4        cli_1.1.0         \n[13] rstudioapi_0.10    yaml_2.2.0         parallel_3.6.1     loo_2.1.0          gridExtra_2.3      withr_2.1.2       \n[19] dplyr_0.8.3        stats4_3.6.1       grid_3.6.1         tidyselect_0.2.5   glue_1.3.1         inline_0.3.15     \n[25] R6_2.4.0           processx_3.4.1     purrr_0.3.3        callr_3.3.2        magrittr_1.5       backports_1.1.6   \n[31] scales_1.0.0       ps_1.3.0           matrixStats_0.55.0 abind_1.4-5        assertthat_0.2.1   colorspace_1.4-1  \n[37] lazyeval_0.2.2     munsell_0.5.0      crayon_1.3.4      ",
    "r_summary_statistic": "posterior R package, version 0.1.2"
  }
}
