{
  "name": "gp_regr",
  "title": "Gaussian Process regression",
  "description": "One-dimensional Gaussian process Regression using the\nexponential quadratic covariance function.",
  "keywords": [
    "stan_benchmark",
    "gaussian process"
  ],
  "references": null,
  "urls": [
    "https://github.com/stan-dev/stat_comp_benchmarks/tree/master/benchmarks/gp_regr"
  ],
  "prior": {
    "keywords": []
  },
  "inputs": { "N": { "type": "int", "dimensions": 0},
              "x": { "type": "real", "dimensions": 1},
              "y": { "type": "real", "dimensions": 1} },
  "model_implementations": {
    "stan": {
      "model_code": "models/stan/gp_regr.stan"
    }
  },
  "added_by": "Mans Magnusson",
  "added_date": "2019-11-20"
}
